test/__init__.py
test/test_client.py
ydapi_sdk/__init__.py
ydapi_sdk/client.py
ydapi_sdk/exceptions.py
ydapi_sdk/tracker.py
ydapi_sdk-0.1.4.dist-info/LICENSE
ydapi_sdk-0.1.4.dist-info/METADATA
ydapi_sdk-0.1.4.dist-info/WHEEL
ydapi_sdk-0.1.4.dist-info/top_level.txt
ydapi_sdk-0.1.4.dist-info/RECORD
