Metadata-Version: 2.2
Name: ydapi_sdk
Version: 0.1.4
Summary: A Python SDK for tracking API requests
Home-page: https://github.com/firework-a/ydapi_sdk
Author: firework-a
Author-email: 2737459675@qq.com
Classifier: Programming Language :: Python :: 3
Classifier: License :: OSI Approved :: MIT License
Classifier: Operating System :: OS Independent
Requires-Python: >=3.10
License-File: LICENSE
Requires-Dist: requests>=2.25.1
Dynamic: author
Dynamic: author-email
Dynamic: classifier
Dynamic: description
Dynamic: description-content-type
Dynamic: home-page
Dynamic: requires-dist
Dynamic: requires-python
Dynamic: summary
